LatePenalty/__init__.py
LatePenalty/_modidx.py
LatePenalty/gradescope.py
LatePenalty/nbgrader.py
LatePenalty-0.0.8.dist-info/LICENSE
LatePenalty-0.0.8.dist-info/METADATA
LatePenalty-0.0.8.dist-info/WHEEL
LatePenalty-0.0.8.dist-info/entry_points.txt
LatePenalty-0.0.8.dist-info/top_level.txt
LatePenalty-0.0.8.dist-info/RECORD
