Metadata-Version: 2.1
Name: LatePenalty
Version: 0.0.8
Summary: Apply Late Penalty to Gradescope Submission to Canvas
Home-page: https://github.com/scott-yj-yang/LatePenalty
Author: Scott Yang
Author-email: yuy004@ucsd.edu
License: Apache Software License 2.0
Keywords: nbdev jupyter notebook python
Classifier: Development Status :: 4 - Beta
Classifier: Intended Audience :: Developers
Classifier: Natural Language :: English
Classifier: Programming Language :: Python :: 3.7
Classifier: Programming Language :: Python :: 3.8
Classifier: Programming Language :: Python :: 3.9
Classifier: Programming Language :: Python :: 3.10
Classifier: License :: OSI Approved :: Apache Software License
Requires-Python: >=3.7
License-File: LICENSE
Requires-Dist: fastcore
Requires-Dist: pandas
Requires-Dist: canvasapi
Requires-Dist: numpy
Requires-Dist: nbformat
Provides-Extra: dev
Requires-Dist: nbdev; extra == "dev"
